fakeshot/__init__.py
fakeshot/__main__.py
fakeshot/generate_csv.py
fakeshot/generate_exr.py
fakeshot/generate_shots.py
fakeshot/logger.py
fakeshot/template.py
fakeshot-0.3.2.dist-info/LICENSE.md
fakeshot-0.3.2.dist-info/METADATA
fakeshot-0.3.2.dist-info/WHEEL
fakeshot-0.3.2.dist-info/entry_points.txt
fakeshot-0.3.2.dist-info/RECORD
