Metadata-Version: 2.3
Name: fakeshot
Version: 0.3.2
Summary: Generate dummy EXR files for VFX pipeline testing.
Keywords: vfx,exr,openexr,pipeline,testing,dummy,placeholder,renders,shots
Author: virgilsisoe
Author-email: 28490646+sisoe24@users.noreply.github.com
Requires-Python: >=3.10,<3.14
Classifier: Intended Audience :: Developers
Classifier: Intended Audience :: Other Audience
Classifier: Topic :: Multimedia :: Graphics
Classifier: Topic :: Software Development :: Testing
Classifier: Topic :: Utilities
Classifier: License :: OSI Approved :: MIT License
Classifier: Programming Language :: Python :: 3
Classifier: Programming Language :: Python :: 3.10
Classifier: Programming Language :: Python :: 3.11
Classifier: Programming Language :: Python :: 3.12
Classifier: Programming Language :: Python :: 3.13
Classifier: Operating System :: OS Independent
Requires-Dist: numpy (==2.2.6)
Requires-Dist: openexr (>=3.3.3,<4.0.0)
Requires-Dist: pillow (>=11.2.1,<12.0.0)
Project-URL: Homepage, https://github.com/sisoe24/fakeshot
Project-URL: Issues, https://github.com/sisoe24/fakeshot/issues
Project-URL: Repository, https://github.com/sisoe24/fakeshot
